robotframework_pykafka/__init__.py
robotframework_pykafka/kafka_helper.py
robotframework_pykafka/robotframework_pykafka.py
robotframework_pykafka/utils.py
robotframework_pykafka-0.12.dist-info/LICENSE.txt
robotframework_pykafka-0.12.dist-info/METADATA
robotframework_pykafka-0.12.dist-info/WHEEL
robotframework_pykafka-0.12.dist-info/top_level.txt
robotframework_pykafka-0.12.dist-info/RECORD
