Metadata-Version: 2.1
Name: robotframework-pykafka
Version: 0.12
Summary: This is a robot framework wrapper around pykafka, the best python kafka library out there as of this writing, and the only one that supports kafka 1.0 through and 2.3.
Home-page: https://github.com/invadergir/robotframework-pykafka
Author: Michael Sesterhenn
Author-email: invadergir@users.noreply.github.com
License: UNKNOWN
Download-URL: https://github.com/invadergir/robotframework_pykafka/tarball/0.11
Keywords: robotframework,kafka,testing
Platform: UNKNOWN
Classifier: Programming Language :: Python :: 3
Classifier: Topic :: Software Development :: Libraries :: Python Modules
Requires-Python: >=3.5
Requires-Dist: robotframework (>=3.2.1)
Requires-Dist: pykafka (>=2.8.0)
